MEGNetSparse/__init__.py
MEGNetSparse/dense2sparse.py
MEGNetSparse/eos.py
MEGNetSparse/layers.py
MEGNetSparse/losses.py
MEGNetSparse/model.py
MEGNetSparse/struct2graph.py
MEGNetSparse/trainer.py
MEGNetSparse/utils.py
megnetsparse-0.0.10.dist-info/METADATA
megnetsparse-0.0.10.dist-info/WHEEL
megnetsparse-0.0.10.dist-info/licenses/LICENSE
megnetsparse-0.0.10.dist-info/RECORD
