Metadata-Version: 2.1
Name: MEGNetSparse
Version: 0.0.10
Project-URL: Homepage, https://github.com/HSE-LAMBDA/MEGNetSparse
Author-email: Romanov Ignat <romanov.ignat.p@gmail.com>
License-File: LICENSE
Requires-Python: >=3.8
Requires-Dist: joblib
Requires-Dist: numpy
Requires-Dist: pymatgen
Requires-Dist: tqdm
